{
  "kind": "coverage_report",
  "version": "1.0",
  "generatedAt": "2026-02-17T00:38:02.225Z",
  "sources": {
    "buildRequest": true,
    "implementationPlan": true
  },
  "requirements": {
    "total": 2,
    "implemented": 1,
    "items": [
      {
        "id": "REQ-1",
        "summary": "Update the backend registration API to return a specific, non-ambiguous error when registration fails (e.g., distinguish between: caller is not a guest/already registered, username already taken, email already taken) instead of returning `null` for all failure cases.",
        "status": "unknown",
        "plannedFiles": [],
        "matchedFiles": []
      },
      {
        "id": "REQ-2",
        "summary": "Update the frontend registration flow to map backend registration failure reasons to accurate, user-friendly English messages (do not show 'Username or email is already taken' unless the backend explicitly indicates username/email collision).",
        "status": "implemented",
        "plannedFiles": [
          "frontend/src/auth/authMessages.ts",
          "frontend/src/auth/AuthProvider.tsx",
          "frontend/src/pages/LoginScreen.tsx"
        ],
        "matchedFiles": [
          "frontend/src/auth/authMessages.ts",
          "frontend/src/auth/AuthProvider.tsx",
          "frontend/src/pages/LoginScreen.tsx"
        ]
      }
    ]
  },
  "changedFiles": [
    "backend/main.mo",
    "build-request.json",
    "feature_evidence.json",
    "frontend-file-summaries.txt",
    "frontend-implementation-plan.json",
    "frontend/src/auth/AuthProvider.tsx",
    "frontend/src/auth/authMessages.ts",
    "frontend/src/backend.d.ts",
    "frontend/src/backend.ts",
    "frontend/src/declarations/backend.did.d.ts",
    "frontend/src/declarations/backend.did.js",
    "frontend/src/pages/LoginScreen.tsx",
    "project_state.json",
    "scratch/component-selection.json",
    "spec.md",
    "spec_vs_diff_report.json"
  ]
}